{
    "version": "0.0.1",
    "architecture": {
        "32bit": {
            "url": "https://github.com/covoyage/kairoa-cli/releases/download/v0.0.1/kairoa-cli_0.0.1_windows_i386.zip",
            "bin": [
                "kairoa.exe"
            ],
            "hash": "c563159c3628579942f051e2453b9c3a46c8eacc3e36ac15eb6750039f6ba7c9"
        },
        "64bit": {
            "url": "https://github.com/covoyage/kairoa-cli/releases/download/v0.0.1/kairoa-cli_0.0.1_windows_x86_64.zip",
            "bin": [
                "kairoa.exe"
            ],
            "hash": "e67ee5e0abdbc3993a93083140c4acd503bfa3779ef8f235c5018c1c1f31dc4e"
        }
    },
    "homepage": "https://github.com/covoyage/kairoa-cli",
    "license": "AGPL-3.0",
    "description": "Kairoa CLI - A developer toolbox with 50+ utilities"
}
